constspace/__init__.py
constspace/core.py
constspace/experimental.py
constspace/py.typed
constspace-0.1.5.dist-info/METADATA
constspace-0.1.5.dist-info/WHEEL
constspace-0.1.5.dist-info/licenses/LICENSE
constspace-0.1.5.dist-info/RECORD
