Metadata-Version: 2.4
Name: constspace
Version: 0.1.5
Summary: A tiny library for read-only, non-instantiable namespace constants.
Project-URL: Homepage, https://github.com/fluffydogcatmouse/constspace
Project-URL: Bug Tracker, https://github.com/fluffydogcatmouse/constspace/issues
Project-URL: Source Code, https://github.com/fluffydogcatmouse/constspace
Author-email: fluffydogcatmouse <franklin_zhang2089@qq.com>
License-File: LICENSE
Classifier: License :: OSI Approved :: MIT License
Classifier: Operating System :: OS Independent
Classifier: Programming Language :: Python :: 3
Requires-Python: >=3.7
